mobotix_finder/__about__.py
mobotix_finder/find_mobotix.py
mobotix_finder-0.2.dist-info/METADATA
mobotix_finder-0.2.dist-info/WHEEL
mobotix_finder-0.2.dist-info/entry_points.txt
mobotix_finder-0.2.dist-info/licenses/LICENSE.txt
mobotix_finder-0.2.dist-info/RECORD
